amalgam/__init__.py
amalgam/api.py
amalgam/lib/version.json
amalgam/lib/darwin/amd64/amalgam-mt-noavx.dylib
amalgam/lib/darwin/amd64/amalgam-mt.dylib
amalgam/lib/darwin/amd64/amalgam-omp.dylib
amalgam/lib/darwin/amd64/amalgam-st.dylib
amalgam/lib/darwin/amd64/docs/version.json
amalgam/lib/darwin/arm64/amalgam-mt.dylib
amalgam/lib/darwin/arm64/amalgam-omp.dylib
amalgam/lib/darwin/arm64/amalgam-st.dylib
amalgam/lib/darwin/arm64/docs/version.json
amalgam/lib/linux/amd64/amalgam-mt-afmi.so
amalgam/lib/linux/amd64/amalgam-mt-noavx.so
amalgam/lib/linux/amd64/amalgam-mt.so
amalgam/lib/linux/amd64/amalgam-omp.so
amalgam/lib/linux/amd64/amalgam-st-afmi.so
amalgam/lib/linux/amd64/amalgam-st.so
amalgam/lib/linux/amd64/docs/version.json
amalgam/lib/linux/arm64/amalgam-mt.so
amalgam/lib/linux/arm64/amalgam-omp.so
amalgam/lib/linux/arm64/amalgam-st.so
amalgam/lib/linux/arm64/docs/version.json
amalgam/lib/linux/arm64_8a/amalgam-st.so
amalgam/lib/linux/arm64_8a/docs/version.json
amalgam/lib/windows/amd64/amalgam-mt-noavx.dll
amalgam/lib/windows/amd64/amalgam-mt.dll
amalgam/lib/windows/amd64/amalgam-omp.dll
amalgam/lib/windows/amd64/amalgam-st.dll
amalgam/lib/windows/amd64/docs/version.json
amalgam_lang-25.3.0.dist-info/licenses/LICENSE.txt
amalgam_lang-25.3.0.dist-info/METADATA
amalgam_lang-25.3.0.dist-info/WHEEL
amalgam_lang-25.3.0.dist-info/top_level.txt
amalgam_lang-25.3.0.dist-info/RECORD
